py_grafana_render/__init__.py
py_grafana_reporter-0.1.3.dist-info/METADATA
py_grafana_reporter-0.1.3.dist-info/WHEEL
py_grafana_reporter-0.1.3.dist-info/RECORD
