Metadata-Version: 2.3
Name: py-grafana-reporter
Version: 0.1.3
Summary: 
Author: YiZixuan
Author-email: sqkkyzx@qq.com
Requires-Python: >=3.12,<4.0
Classifier: Programming Language :: Python :: 3
Classifier: Programming Language :: Python :: 3.12
Classifier: Programming Language :: Python :: 3.13
Requires-Dist: playwright (>=1.49,<2.0)
